AUTHORS
LICENSE
MANIFEST.in
README.rst
setup.py
django_paintstore.egg-info/PKG-INFO
django_paintstore.egg-info/SOURCES.txt
django_paintstore.egg-info/dependency_links.txt
django_paintstore.egg-info/not-zip-safe
django_paintstore.egg-info/top_level.txt
paintstore/__init__.py
paintstore/fields.py
paintstore/models.py
paintstore/widgets.py
paintstore/static/paintstore/colorpicker.js
paintstore/static/paintstore/css/colorpicker.css
paintstore/static/paintstore/images/colorpicker_background.png
paintstore/static/paintstore/images/colorpicker_hex.png
paintstore/static/paintstore/images/colorpicker_hsb_b.png
paintstore/static/paintstore/images/colorpicker_hsb_h.png
paintstore/static/paintstore/images/colorpicker_hsb_s.png
paintstore/static/paintstore/images/colorpicker_indic.gif
paintstore/static/paintstore/images/colorpicker_overlay.png
paintstore/static/paintstore/images/colorpicker_rgb_b.png
paintstore/static/paintstore/images/colorpicker_rgb_g.png
paintstore/static/paintstore/images/colorpicker_rgb_r.png
paintstore/static/paintstore/images/colorpicker_select.gif
paintstore/static/paintstore/images/colorpicker_submit.png
paintstore/static/paintstore/images/select.png
paintstore/static/paintstore/images/select2.png