Metadata-Version: 1.0
Name: django-paintstore
Version: 0.1.2
Summary: A Django app that integrates jQuery ColorPicker with the Django admin.
Home-page: https://github.com/gsiegman/django-paintstore
Author: Glenn Siegman
Author-email: gsiegman@gsiegman.com
License: MIT
Platform: UNKNOWN
Classifier: Development Status :: 4 - Beta
Classifier: Environment :: Web Environment
Classifier: Framework :: Django
Classifier: Intended Audience :: Developers
Classifier: License :: OSI Approved :: MIT License
Classifier: Operating System :: OS Independent
Classifier: Programming Language :: Python
Classifier: Topic :: Utilities
